{
    "status": "True",
    "message": "SUCCESS",
    "errorcode": "",
    "data": [
        {
            "variety": "None",
            "ordertype": "MARKET",
            "producttype": "DELIVERY",
            "duration": "DAY",
            "price": "0.00",
            "triggerprice": "0",
            "quantity": "20",
            "disclosedquantity": "0",
            "squareoff": "0",
            "stoploss": "0",
            "trailingstoploss": "0",
            "tradingsymbol": "ACC",
            "transactiontype": "BUY",
            "exchange": "NSE",
            "symboltoken": "22",
            "instrumenttype": "EQUITY",
            "strikeprice": "0",
            "optiontype": "XX",
            "expirydate": "2025-Feb-11",
            "lotsize": "0",
            "cancelsize": "0",
            "averageprice": "0",
            "filledshares": "0",
            "unfilledshares": "0",
            "orderid": "1131250211100",
            "text": "",
            "status": "Transit",
            "orderstatus": "Transit",
            "updatetime": "2025-Feb-11 10: 20: 34",
            "exchtime": "",
            "exchorderupdatetime": "2025-Feb-11 10: 20: 34",
            "fillid": "",
            "filltime": "",
            "parentorderid": "",
            "uniqueorderid": "",
            "exchangeorderid": "0"
        }
    ]
}